obfuscator/__init__.py
obfuscator/apps.py
obfuscator/cli.py
obfuscator/conf.py
obfuscator/utils.py
obfuscator/management/__init__.py
obfuscator/management/commands/__init__.py
obfuscator/management/commands/obfuscate.py
obfuscator/tests/__init__.py
obfuscator/tests/settings.py
obfuscator/tests/test_commands.py
obfuscator/tests/test_conf.py
obfuscator/tests/test_utils.py
django_db_obfuscator-0.5.3.dist-info/AUTHORS.rst
django_db_obfuscator-0.5.3.dist-info/LICENSE
django_db_obfuscator-0.5.3.dist-info/METADATA
django_db_obfuscator-0.5.3.dist-info/WHEEL
django_db_obfuscator-0.5.3.dist-info/entry_points.txt
django_db_obfuscator-0.5.3.dist-info/top_level.txt
django_db_obfuscator-0.5.3.dist-info/RECORD
