Metadata-Version: 2.1
Name: django-db-obfuscator
Version: 0.5.3
Summary: Django app to obfuscate text data.
Home-page: https://github.com/oesah/django-db-obfuscator
Author: Oezer Sahin
Author-email: os@oesah.ch
License: MIT license
Keywords: obfuscator
Platform: UNKNOWN
Classifier: Environment :: Web Environment
Classifier: Framework :: Django
Classifier: Framework :: Django :: 1.11
Classifier: Framework :: Django :: 2.2
Classifier: Development Status :: 2 - Pre-Alpha
Classifier: Intended Audience :: Developers
Classifier: License :: OSI Approved :: MIT License
Classifier: Natural Language :: English
Classifier: Programming Language :: Python :: 3
Classifier: Programming Language :: Python :: 3.6
Classifier: Programming Language :: Python :: 3.7
Classifier: Programming Language :: Python :: 3.8
Requires-Python: >=3.6
Requires-Dist: setuptools-git (>=1.2)
